{
    "os": "Linux-6.8.0-59-generic-x86_64-with-glibc2.35",
    "python": "CPython 3.10.16",
    "heartbeatAt": "2025-05-19T07:32:58.093997",
    "startedAt": "2025-05-19T07:32:57.887768",
    "docker": null,
    "args": [
        "service",
        "--debug",
        "--port-filename",
        "/tmp/tmpixk4idri/port-622574.txt",
        "--pid",
        "622574"
    ],
    "state": "running",
    "program": "/home/jay/da6401_assignment3/train.py",
    "codePathLocal": "train.py",
    "codePath": "train.py",
    "git": {
        "remote": "https://github.com/jaygupta907/da6401_assignment3.git",
        "commit": "ccbb85cfb8f61bb1331f90a8d46d34d118c9e324"
    },
    "email": "ae21b026@smail.iitm.ac.in",
    "root": "/home/jay/da6401_assignment3",
    "host": "rafalkocielnik-System-Product-Name",
    "username": null,
    "executable": "/home/jay/miniconda3/envs/Sequence/bin/python",
    "cpu_count": 12,
    "cpu_count_logical": 24,
    "cpu_freq": {
        "current": 3360.5146666666665,
        "min": 400.0,
        "max": 5733.0
    },
    "cpu_freq_per_core": [
        {
            "current": 2946.667,
            "min": 400.0,
            "max": 5733.0
        },
        {
            "current": 3278.176,
            "min": 400.0,
            "max": 5733.0
        },
        {
            "current": 3004.644,
            "min": 400.0,
            "max": 5733.0
        },
        {
            "current": 2593.202,
            "min": 400.0,
            "max": 5733.0
        },
        {
            "current": 3004.644,
            "min": 400.0,
            "max": 5733.0
        },
        {
            "current": 4924.956,
            "min": 400.0,
            "max": 5733.0
        },
        {
            "current": 3004.644,
            "min": 400.0,
            "max": 5733.0
        },
        {
            "current": 3004.644,
            "min": 400.0,
            "max": 5733.0
        },
        {
            "current": 5391.068,
            "min": 400.0,
            "max": 5733.0
        },
        {
            "current": 3004.644,
            "min": 400.0,
            "max": 5733.0
        },
        {
            "current": 5453.69,
            "min": 400.0,
            "max": 5733.0
        },
        {
            "current": 2706.07,
            "min": 400.0,
            "max": 5733.0
        },
        {
            "current": 3004.644,
            "min": 400.0,
            "max": 5733.0
        },
        {
            "current": 3004.644,
            "min": 400.0,
            "max": 5733.0
        },
        {
            "current": 3004.644,
            "min": 400.0,
            "max": 5733.0
        },
        {
            "current": 3004.644,
            "min": 400.0,
            "max": 5733.0
        },
        {
            "current": 3004.644,
            "min": 400.0,
            "max": 5733.0
        },
        {
            "current": 3004.644,
            "min": 400.0,
            "max": 5733.0
        },
        {
            "current": 3064.152,
            "min": 400.0,
            "max": 5733.0
        },
        {
            "current": 2687.154,
            "min": 400.0,
            "max": 5733.0
        },
        {
            "current": 5375.29,
            "min": 400.0,
            "max": 5733.0
        },
        {
            "current": 2719.887,
            "min": 400.0,
            "max": 5733.0
        },
        {
            "current": 5733.0,
            "min": 400.0,
            "max": 5733.0
        },
        {
            "current": 3004.644,
            "min": 400.0,
            "max": 5733.0
        }
    ],
    "disk": {
        "/": {
            "total": 3936290357248,
            "used": 3306038853632
        }
    },
    "gpu": "NVIDIA GeForce RTX 4090",
    "gpu_count": 1,
    "gpu_devices": [
        {
            "name": "NVIDIA GeForce RTX 4090",
            "memory_total": 25757220864
        }
    ],
    "memory": {
        "total": 66592837632
    }
}
